pentoy/__init__.py
pentoy/__main__.py
pentoy/__version__.py
pentoy/builder.py
pentoy/cli.py
pentoy/config.py
pentoy/constants.py
pentoy/deploy.py
pentoy/exceptions.py
pentoy/executor.py
pentoy/logger.py
pentoy/parser.py
pentoy/project.py
pentoy/server.py
pentoy/utils.py
pentoy/boilerplate/themes/simple/layout/base.html
pentoy/boilerplate/themes/simple/layout/index.html
pentoy-0.0.2.dist-info/DESCRIPTION.rst
pentoy-0.0.2.dist-info/METADATA
pentoy-0.0.2.dist-info/RECORD
pentoy-0.0.2.dist-info/WHEEL
pentoy-0.0.2.dist-info/entry_points.txt
pentoy-0.0.2.dist-info/metadata.json
pentoy-0.0.2.dist-info/top_level.txt
