Metadata-Version: 2.0
Name: pentoy
Version: 0.0.2
Summary: A light static site generator written in Python.
Home-page: https://github.com/isudox/pentoy
Author: sudoz
Author-email: me@isudox.com
License: MIT
Platform: UNKNOWN
Classifier: License :: OSI Approved :: MIT License
Classifier: Programming Language :: Python
Classifier: Programming Language :: Python :: 3
Classifier: Programming Language :: Python :: 3.3
Classifier: Programming Language :: Python :: 3.4
Classifier: Programming Language :: Python :: 3.5
Classifier: Programming Language :: Python :: 3.6
Classifier: Programming Language :: Python :: Implementation :: CPython
Classifier: Programming Language :: Python :: Implementation :: PyPy
Requires-Dist: pip
Requires-Dist: click
Requires-Dist: jinja2
Requires-Dist: crayons
Requires-Dist: requests (>=2.18.0)
Requires-Dist: mistune
Requires-Dist: pygments
Requires-Dist: werkzeug
Requires-Dist: semver
